superrequests/__init__.py
superrequests-0.1.2.dist-info/METADATA
superrequests-0.1.2.dist-info/WHEEL
superrequests-0.1.2.dist-info/RECORD
